py_optional/__init__.py
py_optional/optional.py
py_optional_chain-0.0.3.dist-info/METADATA
py_optional_chain-0.0.3.dist-info/WHEEL
py_optional_chain-0.0.3.dist-info/top_level.txt
py_optional_chain-0.0.3.dist-info/RECORD
