Metadata-Version: 2.1
Name: py-optional-chain
Version: 0.0.3
Summary: Optional Chain like in Java
Author: wysohn
Author-email: wysohn2002@naver.com
Requires-Python: >=3.6
